unopygifconvt_test/__init__.py
unopygifconvt_test/converter.py
unopygifconvt_test-1.0.0.dist-info/LICENSE
unopygifconvt_test-1.0.0.dist-info/METADATA
unopygifconvt_test-1.0.0.dist-info/WHEEL
unopygifconvt_test-1.0.0.dist-info/top_level.txt
unopygifconvt_test-1.0.0.dist-info/RECORD
